Workbook

Sheet Dashboard
A1: ContexureEarth Tutor Project Command Center
A2: Purpose | B2: Vision-linked project planner covering what is already done, what remains, dependencies, launch gates, risks, research, and metrics.
A3: North Star | B3: Weekly completed tutor actions
A4: Last Updated | B4: 46186
A6: KPI | B6: Value | C6: Meaning
A7: Total Tasks | B7: =COUNTA('Master Plan'!A2:A200) -> 96 | C7: All tracked tasks
A8: Done Tasks | B8: =COUNTIF('Master Plan'!H2:H200,"Done") -> 22 | C8: Completed BizzNexx/ContexureEarth work
A9: Open P0 Tasks | B9: =COUNTIFS('Master Plan'!G2:G200,"P0",'Master Plan'!H2:H200,"<>Done") -> 44 | C9: Critical work left
A10: Blocked Tasks | B10: =COUNTIF('Master Plan'!H2:H200,"Blocked") -> 0 | C10: Needs founder/engineering attention
A11: Open Critical Risks | B11: =COUNTIFS('Risk Register'!D2:D100,"Critical",'Risk Register'!H2:H100,"Open") -> 0 | C11: No launch with critical open risk
A12: Private Beta Gate Date | B12: 46271 | C12: Current target gate
A14: Phase | B14: Start | C14: End | D14: Mission
A15: Already Done / Existing BizzNexx Assets | B15: 46174 | C15: 46186
A16: Foundation & Product Definition | B16: 46188 | C16: 46201
A17: Concierge Prototype | B17: 46202 | C17: 46222
A18: Private Beta | B18: 46223 | C18: 46271
A19: Paid Pilot | B19: 46272 | C19: 46369
A20: Public Launch V1 | B20: 46370 | C20: 46460
A21: Growth & Intelligence V1 | B21: 46461 | C21: 46642
A22: Learning Context V1 | B22: 46643 | C22: 46824
A23: Institution Expansion | B23: 46825 | C23: 47299

Sheet Master Plan
A1: Task ID | B1: Phase | C1: Workstream | D1: Title | E1: Description | F1: Owner | G1: Priority | H1: Status | I1: Start | J1: End | K1: Dependencies | L1: Effort | M1: Acceptance Criteria | N1: Validation Signal | O1: Vision Link | P1: Notes
A2: DONE-001 | B2: D0 | C2: Strategy & Product Definition | D2: Learning Studio strategy created | E2: Created Learning Studio business ontology, strategy plan, execution plan, and beta rollout readiness plan. | F2: Founder/Product | G2: P0 | H2: Done | I2: 46174 | J2: 46179 | L2: 3 | M2: Strategy docs exist and define tutor wedge. | N2: Learning Studio is defined as trust, trial, parent communication, and recurring-fee business. | O2: V1/V2/V4/V5
A3: DONE-002 | B3: D0 | C3: Strategy & Product Definition | D3: First validation wedge narrowed | E3: Narrowed initial beta wedge to Ananya Learning Studio and tutor/coach persona. | F3: Founder/Product | G3: P0 | H3: Done | I3: 46178 | J3: 46179 | K3: DONE-001 | L3: 3 | M3: Ananya is the demo anchor. | N3: Product can be reviewed through one concrete tutor story. | O3: V1
A4: DONE-003 | B4: D0 | C4: Frontend Engineering | D4: Parallel Beta Studio UI added | E4: Added Beta Studio tab for tutor businesses while preserving existing prototype screens. | F4: Frontend | G4: P0 | H4: Done | I4: 46179 | J4: 46180 | K4: DONE-002 | L4: 3 | M4: Tutor-specific surface exists. | N4: Reviewer can open Ananya Learning Studio Beta Studio. | O4: V1/V7
A5: DONE-004 | B5: D0 | C5: Frontend Engineering | D5: Parent-ready Learning Studio surface built | E5: Added teacher credibility, proof, course cards, trial inquiry form, parent journey, trial action queue, monthly fee actions, and FAQ. | F5: Frontend/Product | G5: P0 | H5: Done | I5: 46179 | J5: 46180 | K5: DONE-003 | L5: 3 | M5: Core tutor beta UI exists. | N5: The demo can show parent page to fee workflow. | O5: V1/V2/V4/V5/V6
A6: DONE-005 | B6: D0 | C6: Auth, Privacy & Trust | D6: Beta safety notes added | E6: Added beta disclaimer, beta terms view, and inquiry consent/data-use copy. | F6: Security/Product | G6: P0 | H6: Done | I6: 46180 | J6: 46181 | K6: DONE-004 | L6: 3 | M6: Beta users see scope and data-use notes. | N6: No real-data review without safety copy. | O6: V7
A7: DONE-006 | B7: D0 | C7: Backend & Data Model | D7: Ananya seed data enriched | E7: Aligned backend demo seed data with richer Learning Studio story, persona statuses, and message templates. | F7: Backend/Product | G7: P0 | H7: Done | I7: 46180 | J7: 46181 | K7: DONE-004 | L7: 3 | M7: Seed data supports realistic demo. | N7: Ananya data includes courses, proof, FAQs, leads, payments. | O7: V1/V2/V5
A8: DONE-007 | B8: D0 | C8: Auth, Privacy & Trust | D8: Private beta access controls added | E8: Added optional frontend access code, backend API key gate, environment examples, and production-safe settings hooks. | F8: Security/Backend/Frontend | G8: P0 | H8: Done | I8: 46181 | J8: 46182 | K8: DONE-005 | L8: 3 | M8: Beta access can be restricted. | N8: Demo can be shared with selected reviewers only. | O8: V7
A9: DONE-008 | B9: D0 | C9: Infrastructure & Deployment | D9: Deployment blueprint prepared | E9: Added Postgres support, Gunicorn, static root, render.yaml, health endpoint, and deployment docs. | F9: Engineering | G9: P0 | H9: Done | I9: 46182 | J9: 46183 | K9: DONE-007 | L9: 3 | M9: Render deployment path exists. | N9: Backend health endpoint available. | O9: V7
A10: DONE-009 | B10: D0 | C10: Infrastructure & Deployment | D10: GitHub Actions CI added | E10: Added frontend build and backend checks on main. | F10: Engineering/QA | G10: P0 | H10: Done | I10: 46183 | J10: 46183 | K10: DONE-008 | L10: 3 | M10: CI workflow exists. | N10: Build/check pipeline can run on main. | O10: V7
A11: DONE-010 | B11: D0 | C11: Infrastructure & Deployment | D11: GitHub Pages preview workflow added | E11: Added no-new-cloud-account frontend preview path for UI-only guided review. | F11: Engineering | G11: P1 | H11: Done | I11: 46183 | J11: 46183 | K11: DONE-009 | L11: 3 | M11: Preview workflow and guide exist. | N11: UI can be reviewed without backend hosting. | O11: V1
A12: DONE-011 | B12: D0 | C12: Documentation & Handoff | D12: Root README updated | E12: Updated README with BizzNexx product shape, Learning Studio beta, run commands, and deployment paths. | F12: Documentation | G12: P0 | H12: Done | I12: 46183 | J12: 46184 | K12: DONE-008 | L12: 3 | M12: README gives clear project entry. | N12: New reviewer can understand current status. | O12: V7
A13: DONE-012 | B13: D0 | C13: Operator Setup & Support | D13: Beta review guide created | E13: Created guided review script for tutor beta reviews. | F13: Operations/Product | G13: P0 | H13: Done | I13: 46184 | J13: 46184 | K13: DONE-004 | L13: 3 | M13: Review guide covers parent page, inquiry, action queue, fees, and WTP. | N13: Beta calls have a consistent script. | O13: V1/V2/V5
A14: DONE-013 | B14: D0 | C14: Operator Setup & Support | D14: Beta feedback form created | E14: Created structured beta feedback form with workflow fit, commercial signal, trust/safety, and product gaps. | F14: Operations/Product | G14: P0 | H14: Done | I14: 46184 | J14: 46184 | K14: DONE-012 | L14: 3 | M14: Feedback form can be used per reviewer. | N14: WTP and product-fit signals are captured. | O14: V7
... A18: DONE-017 | B18: D0 | C18: Documentation & Handoff | D18: Team handoff guide created | E18: Created TEAM_HANDOFF_START_HERE.md with mission, decisions, MVP spine, first tasks, repo structure, and QA gates. | F18: Documentation/Product | G18: P0 | H18: Done | I18: 46186 | J18: 46186 | K18: DONE-016 | L18: 3 | M18: Team entry point exists. | N18: New contributor can start from handoff guide. | O18: V7
A19: DONE-018 | B19: D0 | C19: Strategy & Product Definition | D19: ContexureEarth vision mind map created | E19: Created product vision mind map and renamed vision file under ContexureEarth. | F19: Founder/Product | G19: P1 | H19: Done | I19: 46186 | J19: 46186 | L19: 3 | M19: Vision file exists under final name. | N19: Long-term learning intelligence direction captured. | O19: V8/V9/V10
A20: DONE-019 | B20: D0 | C20: Strategy & Product Definition | D20: ContexureEarth tutor roadmap created | E20: Created research-backed tutor product roadmap linking BizzNexx work to ContexureEarth. | F20: Product | G20: P1 | H20: Done | I20: 46186 | J20: 46186 | K20: DONE-018 | L20: 3 | M20: Roadmap covers research, build, GTM, launch, post-launch. | N20: Execution path is visible. | O20: V1-V10
A21: DONE-020 | B21: D0 | C21: Strategy & Product Definition | D21: BizzNexx critical evaluation created | E21: Evaluated what BizzNexx already achieves and how it should evolve into ContexureEarth Tutor. | F21: Product | G21: P1 | H21: Done | I21: 46186 | J21: 46186 | K21: DONE-019 | L21: 3 | M21: Evaluation gives brand architecture and product migration recommendation. | N21: Decision: ContexureEarth public brand; BizzNexx operating engine. | O21: V1-V10
A22: DONE-021 | B22: D0 | C22: QA, Testing & Release Gates | D22: Initial verification passed | E22: npm run build, Django check, collectstatic dry run, compileall, and local UI response were verified previously. | F22: Engineering/QA | G22: P0 | H22: Done | I22: 46183 | J22: 46186 | K22: DONE-009 | L22: 3 | M22: Verification evidence recorded in project log. | N22: Prototype is stable enough for deployment prep. | O22: V7
A23: DONE-022 | B23: D0 | C23: Marketing, Sales & Launch | D23: Code pushed to GitHub | E23: Project log records code pushed with key commits for strategy, UI, safety, deployment, and preview. | F23: Engineering | G23: P0 | H23: Done | I23: 46183 | J23: 46186 | K23: DONE-021 | L23: 3 | M23: Commits are recorded. | N23: Remote repo has current work. | O23: V7
A24: IMD-001 | B24: P0 | C24: Infrastructure & Deployment | D24: Create Render Blueprint deployment | E24: Create Render Blueprint from GitHub and let it provision frontend, backend, and Postgres database. | F24: Engineering | G24: P0 | H24: Not Started | I24: 46188 | J24: 46190 | K24: DONE-008,DONE-022 | L24: 4 | M24: Render services exist and deploy successfully. | N24: Hosted API and frontend URLs available. | O24: V7
A25: IMD-002 | B25: P0 | C25: Auth, Privacy & Trust | D25: Wire beta API keys | E25: Copy backend BIZZNEXX_BETA_API_KEY to frontend VITE_BETA_API_KEY and set VITE_BETA_ACCESS_CODE. | F25: Security/Engineering | G25: P0 | H25: Not Started | I25: 46190 | J25: 46191 | K25: IMD-001,DONE-007 | L25: 2 | M25: Frontend and backend keys match; access gate works. | N25: Unauthorized beta access blocked. | O25: V7
A26: IMD-003 | B26: P0 | C26: QA, Testing & Release Gates | D26: Run hosted beta QA checklist | E26: Confirm HTTPS, access gate, Ananya, Beta Studio, inquiry submit, lead creation, message preview, mark paid, beta terms. | F26: QA/Product | G26: P0 | H26: Not Started | I26: 46191 | J26: 46193 | K26: IMD-002,DONE-014 | L26: 3 | M26: QA checklist completed with pass/fail evidence. | N26: No beta user sees broken hosted flow. | O26: V7
A27: IMD-004 | B27: P0 | C27: Research & Customer Discovery | D27: Recruit first 5 tutor reviewers | E27: Use existing networks to schedule guided review calls with academic tutors/coaches. | F27: Founder/Research | G27: P0 | H27: Not Started | I27: 46191 | J27: 46197 | K27: DONE-012,DONE-013 | L27: 3 | M27: 5 calls scheduled or completed. | N27: At least 3 reviewers fit target ICP. | O27: V1/V2/V5
A28: IMD-005 | B28: P0 | C28: Research & Customer Discovery | D28: Capture beta feedback in structured form | E28: Use BETA_FEEDBACK_FORM for every reviewer and summarize share-worthiness, WTP, trust, and gaps. | F28: Research/Product | G28: P0 | H28: Not Started | I28: 46193 | J28: 46201 | K28: IMD-003,IMD-004 | L28: 3 | M28: Each review has completed feedback form. | N28: Evidence informs next sprint. | O28: V7
A29: IMD-006 | B29: P0 | C29: Strategy & Product Definition | D29: Founder decision: brand architecture | E29: Confirm whether public brand is ContexureEarth Tutor with BizzNexx as internal/legacy engine. | F29: Founder | G29: P0 | H29: Not Started | I29: 46193 | J29: 46195 | K29: DONE-020 | L29: 2 | M29: Decision recorded in roadmap and handoff docs. | N29: No confusion in UI/demo language. | O29: V1-V10
A30: IMD-007 | B30: P0 | C30: UX, Design & Copy | D30: UI copy pass for ContexureEarth Tutor | E30: Replace generic microbusiness language in tutor path with learner, parent, course, batch, fee cycle, operating rhythm. | F30: UX/Product | G30: P0 | H30: Not Started | I30: 46195 | J30: 46200 | K30: IMD-006,FE-001 | L30: 4 | M30: Tutor demo uses education-native language. | N30: Reviewers do not perceive it as generic CRM. | O30: V1/V8
A31: C-001 | B31: P0 | C31: Frontend Engineering | D31: Audit current frontend architecture | E31: Identify routes, state, API usage, design debt, responsive gaps, and what can be reused. | F31: Frontend | G31: P0 | H31: Not Started | I31: 46188 | J31: 46191 | K31: DONE-004 | L31: 4 | M31: Frontend audit is documented. | N31: Large implementation changes have a clear base. | O31: V7
... A97: INST-004 | B97: P2 | C97: Institution Expansion | D97: Institution pilot launch | E97: Launch controlled pilot with school, college, or coaching institution. | F97: Founder/Product/GTM | G97: P2 | H97: Not Started | I97: 47209 | J97: 47299 | K97: INST-003 | L97: 8 | M97: Pilot contract, success metrics, support plan, data policy signed. | N97: Institution pilot active. | O97: V10

Sheet Done Inventory
A1: Task ID | B1: Phase | C1: Workstream | D1: Title | E1: Description | F1: Owner | G1: Priority | H1: Status | I1: Start | J1: End | K1: Dependencies | L1: Effort | M1: Acceptance Criteria | N1: Validation Signal | O1: Vision Link | P1: Notes
A2: DONE-001 | B2: D0 | C2: Strategy & Product Definition | D2: Learning Studio strategy created | E2: Created Learning Studio business ontology, strategy plan, execution plan, and beta rollout readiness plan. | F2: Founder/Product | G2: P0 | H2: Done | I2: 46174 | J2: 46179 | L2: 3 | M2: Strategy docs exist and define tutor wedge. | N2: Learning Studio is defined as trust, trial, parent communication, and recurring-fee business. | O2: V1/V2/V4/V5
A3: DONE-002 | B3: D0 | C3: Strategy & Product Definition | D3: First validation wedge narrowed | E3: Narrowed initial beta wedge to Ananya Learning Studio and tutor/coach persona. | F3: Founder/Product | G3: P0 | H3: Done | I3: 46178 | J3: 46179 | K3: DONE-001 | L3: 3 | M3: Ananya is the demo anchor. | N3: Product can be reviewed through one concrete tutor story. | O3: V1
A4: DONE-003 | B4: D0 | C4: Frontend Engineering | D4: Parallel Beta Studio UI added | E4: Added Beta Studio tab for tutor businesses while preserving existing prototype screens. | F4: Frontend | G4: P0 | H4: Done | I4: 46179 | J4: 46180 | K4: DONE-002 | L4: 3 | M4: Tutor-specific surface exists. | N4: Reviewer can open Ananya Learning Studio Beta Studio. | O4: V1/V7
A5: DONE-004 | B5: D0 | C5: Frontend Engineering | D5: Parent-ready Learning Studio surface built | E5: Added teacher credibility, proof, course cards, trial inquiry form, parent journey, trial action queue, monthly fee actions, and FAQ. | F5: Frontend/Product | G5: P0 | H5: Done | I5: 46179 | J5: 46180 | K5: DONE-003 | L5: 3 | M5: Core tutor beta UI exists. | N5: The demo can show parent page to fee workflow. | O5: V1/V2/V4/V5/V6
A6: DONE-005 | B6: D0 | C6: Auth, Privacy & Trust | D6: Beta safety notes added | E6: Added beta disclaimer, beta terms view, and inquiry consent/data-use copy. | F6: Security/Product | G6: P0 | H6: Done | I6: 46180 | J6: 46181 | K6: DONE-004 | L6: 3 | M6: Beta users see scope and data-use notes. | N6: No real-data review without safety copy. | O6: V7
A7: DONE-006 | B7: D0 | C7: Backend & Data Model | D7: Ananya seed data enriched | E7: Aligned backend demo seed data with richer Learning Studio story, persona statuses, and message templates. | F7: Backend/Product | G7: P0 | H7: Done | I7: 46180 | J7: 46181 | K7: DONE-004 | L7: 3 | M7: Seed data supports realistic demo. | N7: Ananya data includes courses, proof, FAQs, leads, payments. | O7: V1/V2/V5
A8: DONE-007 | B8: D0 | C8: Auth, Privacy & Trust | D8: Private beta access controls added | E8: Added optional frontend access code, backend API key gate, environment examples, and production-safe settings hooks. | F8: Security/Backend/Frontend | G8: P0 | H8: Done | I8: 46181 | J8: 46182 | K8: DONE-005 | L8: 3 | M8: Beta access can be restricted. | N8: Demo can be shared with selected reviewers only. | O8: V7
A9: DONE-008 | B9: D0 | C9: Infrastructure & Deployment | D9: Deployment blueprint prepared | E9: Added Postgres support, Gunicorn, static root, render.yaml, health endpoint, and deployment docs. | F9: Engineering | G9: P0 | H9: Done | I9: 46182 | J9: 46183 | K9: DONE-007 | L9: 3 | M9: Render deployment path exists. | N9: Backend health endpoint available. | O9: V7
A10: DONE-009 | B10: D0 | C10: Infrastructure & Deployment | D10: GitHub Actions CI added | E10: Added frontend build and backend checks on main. | F10: Engineering/QA | G10: P0 | H10: Done | I10: 46183 | J10: 46183 | K10: DONE-008 | L10: 3 | M10: CI workflow exists. | N10: Build/check pipeline can run on main. | O10: V7
A11: DONE-010 | B11: D0 | C11: Infrastructure & Deployment | D11: GitHub Pages preview workflow added | E11: Added no-new-cloud-account frontend preview path for UI-only guided review. | F11: Engineering | G11: P1 | H11: Done | I11: 46183 | J11: 46183 | K11: DONE-009 | L11: 3 | M11: Preview workflow and guide exist. | N11: UI can be reviewed without backend hosting. | O11: V1
A12: DONE-011 | B12: D0 | C12: Documentation & Handoff | D12: Root README updated | E12: Updated README with BizzNexx product shape, Learning Studio beta, run commands, and deployment paths. | F12: Documentation | G12: P0 | H12: Done | I12: 46183 | J12: 46184 | K12: DONE-008 | L12: 3 | M12: README gives clear project entry. | N12: New reviewer can understand current status. | O12: V7
A13: DONE-012 | B13: D0 | C13: Operator Setup & Support | D13: Beta review guide created | E13: Created guided review script for tutor beta reviews. | F13: Operations/Product | G13: P0 | H13: Done | I13: 46184 | J13: 46184 | K13: DONE-004 | L13: 3 | M13: Review guide covers parent page, inquiry, action queue, fees, and WTP. | N13: Beta calls have a consistent script. | O13: V1/V2/V5
A14: DONE-013 | B14: D0 | C14: Operator Setup & Support | D14: Beta feedback form created | E14: Created structured beta feedback form with workflow fit, commercial signal, trust/safety, and product gaps. | F14: Operations/Product | G14: P0 | H14: Done | I14: 46184 | J14: 46184 | K14: DONE-012 | L14: 3 | M14: Feedback form can be used per reviewer. | N14: WTP and product-fit signals are captured. | O14: V7
... A18: DONE-017 | B18: D0 | C18: Documentation & Handoff | D18: Team handoff guide created | E18: Created TEAM_HANDOFF_START_HERE.md with mission, decisions, MVP spine, first tasks, repo structure, and QA gates. | F18: Documentation/Product | G18: P0 | H18: Done | I18: 46186 | J18: 46186 | K18: DONE-016 | L18: 3 | M18: Team entry point exists. | N18: New contributor can start from handoff guide. | O18: V7
A19: DONE-018 | B19: D0 | C19: Strategy & Product Definition | D19: ContexureEarth vision mind map created | E19: Created product vision mind map and renamed vision file under ContexureEarth. | F19: Founder/Product | G19: P1 | H19: Done | I19: 46186 | J19: 46186 | L19: 3 | M19: Vision file exists under final name. | N19: Long-term learning intelligence direction captured. | O19: V8/V9/V10
A20: DONE-019 | B20: D0 | C20: Strategy & Product Definition | D20: ContexureEarth tutor roadmap created | E20: Created research-backed tutor product roadmap linking BizzNexx work to ContexureEarth. | F20: Product | G20: P1 | H20: Done | I20: 46186 | J20: 46186 | K20: DONE-018 | L20: 3 | M20: Roadmap covers research, build, GTM, launch, post-launch. | N20: Execution path is visible. | O20: V1-V10
A21: DONE-020 | B21: D0 | C21: Strategy & Product Definition | D21: BizzNexx critical evaluation created | E21: Evaluated what BizzNexx already achieves and how it should evolve into ContexureEarth Tutor. | F21: Product | G21: P1 | H21: Done | I21: 46186 | J21: 46186 | K21: DONE-019 | L21: 3 | M21: Evaluation gives brand architecture and product migration recommendation. | N21: Decision: ContexureEarth public brand; BizzNexx operating engine. | O21: V1-V10
A22: DONE-021 | B22: D0 | C22: QA, Testing & Release Gates | D22: Initial verification passed | E22: npm run build, Django check, collectstatic dry run, compileall, and local UI response were verified previously. | F22: Engineering/QA | G22: P0 | H22: Done | I22: 46183 | J22: 46186 | K22: DONE-009 | L22: 3 | M22: Verification evidence recorded in project log. | N22: Prototype is stable enough for deployment prep. | O22: V7
A23: DONE-022 | B23: D0 | C23: Marketing, Sales & Launch | D23: Code pushed to GitHub | E23: Project log records code pushed with key commits for strategy, UI, safety, deployment, and preview. | F23: Engineering | G23: P0 | H23: Done | I23: 46183 | J23: 46186 | K23: DONE-021 | L23: 3 | M23: Commits are recorded. | N23: Remote repo has current work. | O23: V7

Sheet Remaining Work
A1: Task ID | B1: Phase | C1: Workstream | D1: Title | E1: Description | F1: Owner | G1: Priority | H1: Status | I1: Start | J1: End | K1: Dependencies | L1: Effort | M1: Acceptance Criteria | N1: Validation Signal | O1: Vision Link | P1: Notes
A2: IMD-001 | B2: P0 | C2: Infrastructure & Deployment | D2: Create Render Blueprint deployment | E2: Create Render Blueprint from GitHub and let it provision frontend, backend, and Postgres database. | F2: Engineering | G2: P0 | H2: Not Started | I2: 46188 | J2: 46190 | K2: DONE-008,DONE-022 | L2: 4 | M2: Render services exist and deploy successfully. | N2: Hosted API and frontend URLs available. | O2: V7
A3: IMD-002 | B3: P0 | C3: Auth, Privacy & Trust | D3: Wire beta API keys | E3: Copy backend BIZZNEXX_BETA_API_KEY to frontend VITE_BETA_API_KEY and set VITE_BETA_ACCESS_CODE. | F3: Security/Engineering | G3: P0 | H3: Not Started | I3: 46190 | J3: 46191 | K3: IMD-001,DONE-007 | L3: 2 | M3: Frontend and backend keys match; access gate works. | N3: Unauthorized beta access blocked. | O3: V7
A4: IMD-003 | B4: P0 | C4: QA, Testing & Release Gates | D4: Run hosted beta QA checklist | E4: Confirm HTTPS, access gate, Ananya, Beta Studio, inquiry submit, lead creation, message preview, mark paid, beta terms. | F4: QA/Product | G4: P0 | H4: Not Started | I4: 46191 | J4: 46193 | K4: IMD-002,DONE-014 | L4: 3 | M4: QA checklist completed with pass/fail evidence. | N4: No beta user sees broken hosted flow. | O4: V7
A5: IMD-004 | B5: P0 | C5: Research & Customer Discovery | D5: Recruit first 5 tutor reviewers | E5: Use existing networks to schedule guided review calls with academic tutors/coaches. | F5: Founder/Research | G5: P0 | H5: Not Started | I5: 46191 | J5: 46197 | K5: DONE-012,DONE-013 | L5: 3 | M5: 5 calls scheduled or completed. | N5: At least 3 reviewers fit target ICP. | O5: V1/V2/V5
A6: IMD-005 | B6: P0 | C6: Research & Customer Discovery | D6: Capture beta feedback in structured form | E6: Use BETA_FEEDBACK_FORM for every reviewer and summarize share-worthiness, WTP, trust, and gaps. | F6: Research/Product | G6: P0 | H6: Not Started | I6: 46193 | J6: 46201 | K6: IMD-003,IMD-004 | L6: 3 | M6: Each review has completed feedback form. | N6: Evidence informs next sprint. | O6: V7
A7: IMD-006 | B7: P0 | C7: Strategy & Product Definition | D7: Founder decision: brand architecture | E7: Confirm whether public brand is ContexureEarth Tutor with BizzNexx as internal/legacy engine. | F7: Founder | G7: P0 | H7: Not Started | I7: 46193 | J7: 46195 | K7: DONE-020 | L7: 2 | M7: Decision recorded in roadmap and handoff docs. | N7: No confusion in UI/demo language. | O7: V1-V10
A8: IMD-007 | B8: P0 | C8: UX, Design & Copy | D8: UI copy pass for ContexureEarth Tutor | E8: Replace generic microbusiness language in tutor path with learner, parent, course, batch, fee cycle, operating rhythm. | F8: UX/Product | G8: P0 | H8: Not Started | I8: 46195 | J8: 46200 | K8: IMD-006,FE-001 | L8: 4 | M8: Tutor demo uses education-native language. | N8: Reviewers do not perceive it as generic CRM. | O8: V1/V8
A9: C-001 | B9: P0 | C9: Frontend Engineering | D9: Audit current frontend architecture | E9: Identify routes, state, API usage, design debt, responsive gaps, and what can be reused. | F9: Frontend | G9: P0 | H9: Not Started | I9: 46188 | J9: 46191 | K9: DONE-004 | L9: 4 | M9: Frontend audit is documented. | N9: Large implementation changes have a clear base. | O9: V7
A10: D-001 | B10: P0 | C10: Backend & Data Model | D10: Audit backend models/APIs | E10: Identify model gaps, workflow gaps, auth gaps, migration risks, and generic-to-education naming pressure. | F10: Backend | G10: P0 | H10: Not Started | I10: 46188 | J10: 46191 | K10: DONE-006 | L10: 4 | M10: Backend audit is documented. | N10: Tenant/auth/model decisions can be made. | O10: V7/V8
A11: A-001 | B11: P0 | C11: Strategy & Product Definition | D11: Define production personas | E11: Document academic tutor, exam coach, hobby teacher, skill trainer, fitness trainer, corporate trainer, and priority order. | F11: Product | G11: P0 | H11: Not Started | I11: 46188 | J11: 46190 | K11: DONE-015 | L11: 2 | M11: Persona definitions are approved. | N11: P-AST remains first ICP unless evidence changes. | O11: V1
A12: A-004 | B12: P0 | C12: Strategy & Product Definition | D12: Map public visitor journey | E12: Map parent path from shared link to inquiry, trial CTA, confirmation, and WhatsApp handoff. | F12: Product/UX | G12: P0 | H12: Not Started | I12: 46190 | J12: 46193 | K12: A-001 | L12: 3 | M12: Journey includes trust, course fit, fee clarity, trial, and privacy. | N12: Parent can understand next step in 30 seconds. | O12: V1/V2
A13: A-005 | B13: P0 | C13: Strategy & Product Definition | D13: Map owner inquiry-to-fee journey | E13: Map owner path from inquiry to trial to enrollment to fee tracking and proof/referral prompt. | F13: Product/UX | G13: P0 | H13: Not Started | I13: 46190 | J13: 46194 | K13: A-001 | L13: 3 | M13: Every owner step has status, next action, and message template. | N13: Owner knows what to do today. | O13: V2/V4/V5/V6/V7
... A75: INST-004 | B75: P2 | C75: Institution Expansion | D75: Institution pilot launch | E75: Launch controlled pilot with school, college, or coaching institution. | F75: Founder/Product/GTM | G75: P2 | H75: Not Started | I75: 47209 | J75: 47299 | K75: INST-003 | L75: 8 | M75: Pilot contract, success metrics, support plan, data policy signed. | N75: Institution pilot active. | O75: V10

Sheet Vision Map
A1: Vision ID | B1: Pillar | C1: Founder Belief | D1: Product Translation | E1: Product Surface | F1: Validation Signal
A2: V1 | B2: Tutor Trust Entry | C2: Tutors must look credible before parents inquire. | D2: Public page, proof, FAQ, local context. | E2: Public Trust Page | F2: Tutor says they would share page.
A3: V2 | B3: Structured Context Capture | C3: Raw WhatsApp lacks class, board, concern, timing context. | D3: Inquiry form captures minimum useful learning/business context. | E3: Structured Inquiry | F3: Owner can reply without basic questions.
A4: V3 | B4: WhatsApp-Native Operations | C4: Tutors will not abandon WhatsApp. | D4: Editable click-to-chat templates and action statuses. | E4: WhatsApp Handoff | F4: Owner sends/records follow-ups weekly.
A5: V4 | B5: Trial To Enrollment Discipline | C5: Missed demos leak revenue. | D5: Trial status, reminders, post-trial follow-up, enrolled/lost reasons. | E5: Trial Workflow | F5: Trial outcomes are marked.
A6: V5 | B6: Fee Clarity Without Awkwardness | C6: Recurring cash flow is relationship-sensitive. | D6: Fee cycles, ageing, polite reminders, mark paid/part paid. | E6: Fee Cycle | F6: Tutor tracks at least one real cycle.
A7: V6 | B7: Proof And Referral Loop | C7: Good teaching often stays invisible. | D7: Testimonials, result proof, referral requests, approval workflow. | E7: Proof Loop | F7: Tutor collects proof monthly.
A8: V7 | B8: Owner Operating Rhythm | C8: Dashboard must produce action, not decoration. | D8: Today queue, weekly digest, readiness and source signals. | E8: Operating Rhythm | F8: Weekly completed tutor actions increase.
A9: V8 | B9: Learner Context | C9: The larger vision requires understanding learners beyond marks. | D9: Learner context card, parent goals, confidence, concerns, next action. | E9: Learner Context Card | F9: Tutors use context in parent conversations.
A10: V9 | B10: Practical Learning | C10: Learning must connect to life, work, planet, community. | D10: Project prompts, real-world examples, contextual lesson enrichment. | E10: Practical Learning Engine | F10: Assignments include real-world context.
A11: V10 | B11: Institutional Intelligence | C11: Tutors are entry point to schools/colleges. | D11: Cohort dashboards, intervention tracking, improvement reports. | E11: Institution Dashboards | F11: Institution pilot signed.

Sheet Timeline
A1: Phase ID | B1: Phase | C1: Start | D1: End | E1: Duration Days | F1: Target Gate
A2: D0 | B2: Already Done / Existing BizzNexx Assets | C2: 46174 | D2: 46186 | E2: =D2-C2+1 -> 13
A3: P0 | B3: Foundation & Product Definition | C3: 46188 | D3: 46201 | E3: =D3-C3+1 -> 14
A4: P1 | B4: Concierge Prototype | C4: 46202 | D4: 46222 | E4: =D4-C4+1 -> 21 | F4: Alpha Gate
A5: P2 | B5: Private Beta | C5: 46223 | D5: 46271 | E5: =D5-C5+1 -> 49 | F5: Private Beta Gate
A6: P3 | B6: Paid Pilot | C6: 46272 | D6: 46369 | E6: =D6-C6+1 -> 98 | F6: Paid Pilot Gate
A7: P4 | B7: Public Launch V1 | C7: 46370 | D7: 46460 | E7: =D7-C7+1 -> 91 | F7: Public Launch Gate
A8: P5 | B8: Growth & Intelligence V1 | C8: 46461 | D8: 46642 | E8: =D8-C8+1 -> 182 | F8: Intelligence Gate
A9: P6 | B9: Learning Context V1 | C9: 46643 | D9: 46824 | E9: =D9-C9+1 -> 182 | F9: Learning Context Gate
A10: P7 | B10: Institution Expansion | C10: 46825 | D10: 47299 | E10: =D10-C10+1 -> 475 | F10: Institution Gate

Sheet Dependencies
A1: Task ID | B1: Depends On | C1: Dependency Type | D1: Why It Matters | E1: Blocked If Missing
A2: DONE-002 | B2: DONE-001 | C2: Finish-to-start | D2: Task relies on upstream output being complete. | E2: Yes
A3: DONE-003 | B3: DONE-002 | C3: Finish-to-start | D3: Task relies on upstream output being complete. | E3: Yes
A4: DONE-004 | B4: DONE-003 | C4: Finish-to-start | D4: Task relies on upstream output being complete. | E4: Yes
A5: DONE-005 | B5: DONE-004 | C5: Finish-to-start | D5: Task relies on upstream output being complete. | E5: Yes
A6: DONE-006 | B6: DONE-004 | C6: Finish-to-start | D6: Task relies on upstream output being complete. | E6: Yes
A7: DONE-007 | B7: DONE-005 | C7: Finish-to-start | D7: Task relies on upstream output being complete. | E7: Yes
A8: DONE-008 | B8: DONE-007 | C8: Finish-to-start | D8: Task relies on upstream output being complete. | E8: Yes
A9: DONE-009 | B9: DONE-008 | C9: Finish-to-start | D9: Task relies on upstream output being complete. | E9: Yes
A10: DONE-010 | B10: DONE-009 | C10: Finish-to-start | D10: Task relies on upstream output being complete. | E10: Yes
A11: DONE-011 | B11: DONE-008 | C11: Finish-to-start | D11: Task relies on upstream output being complete. | E11: Yes
A12: DONE-012 | B12: DONE-004 | C12: Finish-to-start | D12: Task relies on upstream output being complete. | E12: Yes
... A164: INST-004 | B164: INST-003 | C164: Finish-to-start | D164: Task relies on upstream output being complete. | E164: Yes

Sheet Launch Gates
A1: Gate | B1: Phase | C1: Target Date | D1: Criteria | E1: Required Tasks | F1: Status | G1: Evidence / Notes
A2: Alpha Gate | B2: P1 | C2: 46222 | D2: Public page works; inquiry flow works; owner queue exists; WhatsApp handoff works; fee tracker exists; demo data labeled. | E2: C-003,C-004,C-005,C-008,F-001 | F2: Not Started
A3: Private Beta Gate | B3: P2 | C3: 46271 | D3: Owner login; tenant isolation; persistence; consent; beta terms; backup plan; smoke tests; mobile QA; support channel. | E3: SEC-010,D-002,E-006,SEC-014,INFRA-010,QA-011 | F3: Not Started
A4: Paid Pilot Gate | B4: P3 | C4: 46369 | D4: Repeatable setup; pricing clear; support docs; source tracking; weekly digest; proof/referral; case template. | E4: GTM-001,OPS-001,DATA-002,FE-020,FE-021,GTM-005 | F4: Not Started
A5: Public Launch Gate | B5: P4 | C5: 46460 | D5: Production monitoring; rollback; privacy; deletion flow; onboarding; billing; conversion dashboard; churn tracking. | E5: INFRA-020,FE-030,GTM-010,DATA-010,QA-020 | F5: Not Started
A6: Intelligence Gate | B6: P5 | C6: 46642 | D6: AI drafts accepted; analytics useful; support load manageable; data safety stable. | E6: AI-001,AI-002,DATA-021,STR-020 | F6: Not Started
A7: Learning Context Gate | B7: P6 | C7: 46824 | D7: Learner context used ethically; parent reports constructive; consent/correction ready. | E7: AI-010,SEC-020,AI-011,AI-012 | F7: Not Started
A8: Institution Gate | B8: P7 | C8: 47299 | D8: Tutor product retained; data privacy mature; institution pilot has signed success criteria. | E8: INST-001,INST-002,INST-003,INST-004 | F8: Not Started

Sheet Risk Register
A1: Risk ID | B1: Risk | C1: Impact | D1: Likelihood | E1: Why It Matters | F1: Mitigation | G1: Owner | H1: Status | I1: Linked Task
A2: R-001 | B2: Identity drift between BizzNexx and ContexureEarth | C2: High | D2: High | E2: Confuses customers and roadmap. | F2: Make ContexureEarth public education brand; BizzNexx internal/legacy engine. | G2: Founder | H2: Open | I2: IMD-006
A3: R-002 | B3: Overbuilding LMS/ERP features | C3: High | D3: Medium | E3: Slows launch and weakens wedge. | F3: Use decision rules and P3 deferral list. | G3: Product | H3: Open | I3: STR-002
A4: R-003 | B4: Tutor expects guaranteed leads | C4: High | D4: Medium | E4: Creates mistrust and churn. | F4: Position as conversion/operations, not marketplace. | G4: GTM | H4: Open | I4: GTM-001
A5: R-004 | B5: Parent/student data leakage | C5: Critical | D5: Low | E5: Trust and legal risk. | F5: Tenant isolation, auth, consent, deletion, minimization. | G5: Security | H5: Open | I5: D-002
A6: R-005 | B6: WhatsApp automation too early | C6: Medium | D6: Medium | E6: Compliance and complexity risk. | F6: Launch manual handoff first. | G6: Product | H6: Open | I6: F-001
A7: R-006 | B7: Fee reminders feel aggressive | C7: Medium | D7: Medium | E7: Relationship damage. | F7: Polite templates and manual review before send. | G7: UX | H7: Open | I7: F-003
A8: R-007 | B8: Weak weekly retention | C8: High | D8: Medium | E8: Product becomes setup service only. | F8: Build owner action rhythm and weekly digest. | G8: Data/Product | H8: Open | I8: DATA-002
A9: R-008 | B9: AI overclaims learner ability | C9: Critical | D9: Medium | E9: Can harm learners and trust. | F9: Human-confirmed, editable, non-judgmental insights. | G9: AI/Security | H9: Open | I9: SEC-020
A10: R-009 | B10: Support burden too high | C10: Medium | D10: Medium | E10: Margins suffer. | F10: Setup SOP, help center, fewer custom workflows. | G10: OPS | H10: Open | I10: OPS-001
A11: R-010 | B11: No paid willingness | C11: High | D11: Medium | E11: Business model not validated. | F11: Paid pilot pricing tests and cancellation interviews. | G11: GTM | H11: Open | I11: GTM-004

Sheet Metrics
A1: Metric Type | B1: Metric | C1: Definition | D1: Cadence | E1: Owner | F1: First Relevant Phase | G1: Target
A2: North Star | B2: Weekly completed tutor actions | C2: Count inquiry replies, trial follow-ups, fee updates, reminders, proof/referral/progress actions completed weekly. | D2: Weekly | E2: Product/Data | F2: P2 | G2: 25+ actions/week across beta by private beta end
A3: Activation | B3: Setup completed | C3: Tutor profile, courses, proof, FAQ, templates and public page ready. | D3: Weekly | E3: OPS | F3: P1 | G3: 70% of onboarded tutors complete setup
A4: Activation | B4: Public page shared | C4: Tutor shares link with parent/prospect. | D4: Weekly | E4: GTM/Data | F4: P1 | G4: 3 of first 5 pilot tutors share page
A5: Activation | B5: First inquiry captured | C5: At least one real inquiry submitted. | D5: Weekly | E5: Product/Data | F5: P1 | G5: 20 real inquiries by concierge exit
A6: Retention | B6: Dashboard weekly active tutors | C6: Tutors visiting action queue weekly. | D6: Weekly | E6: Data | F6: P2 | G6: 50% private beta WAU
A7: Workflow | B7: Inquiry status update rate | C7: Share of inquiries with status updated by owner. | D7: Weekly | E7: Data | F7: P2 | G7: 30%+ in private beta
A8: Revenue | B8: Paid pilot conversion | C8: Beta users converting to paid pilot. | D8: Monthly | E8: GTM | F8: P3 | G8: 10 paid pilots
A9: Revenue | B9: Month-two retention | C9: Paid pilots active in second month. | D9: Monthly | E9: GTM/Data | F9: P3 | G9: 60%+
A10: Quality | B10: Setup time | C10: Time to create share-ready tutor account. | D10: Monthly | E10: OPS | F10: P3 | G10: Under 90 minutes
A11: Learning | B11: Learner context card usage | C11: Learners with useful context card reviewed by tutor. | D11: Monthly | E11: AI/Data | F11: P6 | G11: 50% of active learners in context pilots

Sheet Research Tracker
A1: Research ID | B1: Name | C1: Segment | D1: City | E1: Contact | F1: Status | G1: Scheduled Date | H1: Completed Date | I1: Current Tools | J1: Top Pain | K1: Pain Score 1-5 | L1: WTP Setup | M1: WTP Monthly | N1: Key Quote | O1: Next Step
A2: RCH-001 | F2: Not Contacted
A3: RCH-002 | F3: Not Contacted
A4: RCH-003 | F4: Not Contacted
A5: RCH-004 | F5: Not Contacted
A6: RCH-005 | F6: Not Contacted
A7: RCH-006 | F7: Not Contacted
A8: RCH-007 | F8: Not Contacted
A9: RCH-008 | F9: Not Contacted
A10: RCH-009 | F10: Not Contacted
A11: RCH-010 | F11: Not Contacted
A12: RCH-011 | F12: Not Contacted
A13: RCH-012 | F13: Not Contacted
... A41: RCH-040 | F41: Not Contacted

Sheet Backlog
A1: Backlog ID | B1: Item | C1: Priority | D1: Category | E1: Why It Exists | F1: Trigger To Build | G1: Notes
A2: BKL-001 | B2: Google Forms import | C2: P2 | D2: Scale | E2: Useful for tutors already using Forms. | F2: After native inquiry validates.
A3: BKL-002 | B3: Google Sheets export | C3: P2 | D3: Scale | E3: Useful for trust and data portability. | F3: After paid pilot.
A4: BKL-003 | B4: Payment gateway | C4: P3 | D4: Deferred | E4: Adds complexity before manual fee value proven. | F4: After fee tracker retention.
A5: BKL-004 | B5: Parent mobile app | C5: P3 | D5: Deferred | E5: Too much scope before owner workflow retention. | F5: After institution/tutor demand.
A6: BKL-005 | B6: Full LMS | C6: P3 | D6: Deferred | E6: Competes with LMS and dilutes wedge. | F6: Only if paid users demand.
A7: BKL-006 | B7: WhatsApp Cloud API automation | C7: P2/P3 | D7: Scale | E7: Useful after manual workflow proves value and opt-in is clear. | F7: After 100+ active tutors.
A8: BKL-007 | B8: Corporate trainer proposal workflow | C8: P3 | D8: Deferred | E8: Different ICP and sales cycle. | F8: After tutor engine matures.
A9: BKL-008 | B9: Full test engine | C9: P3 | D9: Deferred | E9: Exam-coach specific and data-heavy. | F9: After exam coach segment validated.

Sheet Summary Data
A1: Status | B1: Count
A2: Done | B2: =COUNTIF('Master Plan'!H:H,"Done") -> 22
A3: In Progress | B3: =COUNTIF('Master Plan'!H:H,"In Progress") -> 0
A4: In Review | B4: =COUNTIF('Master Plan'!H:H,"In Review") -> 0
A5: In QA | B5: =COUNTIF('Master Plan'!H:H,"In QA") -> 0
A6: Blocked | B6: =COUNTIF('Master Plan'!H:H,"Blocked") -> 0
A7: Not Started | B7: =COUNTIF('Master Plan'!H:H,"Not Started") -> 74
A8: Deferred | B8: =COUNTIF('Master Plan'!H:H,"Deferred") -> 0
A10: Priority | B10: Open Count
A11: P0 | B11: =COUNTIFS('Master Plan'!G:G,"P0",'Master Plan'!H:H,"<>Done") -> 44
A12: P1 | B12: =COUNTIFS('Master Plan'!G:G,"P1",'Master Plan'!H:H,"<>Done") -> 15
A13: P2 | B13: =COUNTIFS('Master Plan'!G:G,"P2",'Master Plan'!H:H,"<>Done") -> 15
A14: P3 | B14: =COUNTIFS('Master Plan'!G:G,"P3",'Master Plan'!H:H,"<>Done") -> 0

Sheet Lists
A1: Statuses | B1: Priorities | C1: Phases | D1: Workstreams
A2: Done | B2: P0 | C2: D0 | D2: Strategy & Product Definition
A3: In Progress | B3: P1 | C3: P0 | D3: Research & Customer Discovery
A4: In Review | B4: P2 | C4: P1 | D4: UX, Design & Copy
A5: In QA | B5: P3 | C5: P2 | D5: Frontend Engineering
A6: Blocked | C6: P3 | D6: Backend & Data Model
A7: Not Started | C7: P4 | D7: Auth, Privacy & Trust
A8: Deferred | C8: P5 | D8: WhatsApp & Messaging
C9: P6 | D9: Analytics & Metrics
C10: P7 | D10: Operator Setup & Support
D11: Marketing, Sales & Launch
D12: QA, Testing & Release Gates
D13: Infrastructure & Deployment
D14: AI & Learning Intelligence
D15: Institution Expansion
D16: Documentation & Handoff
